{
  "chapter": 15,
  "sections": [
    {
      "title": "Kosakata 1 (어휘 1)",
      "type": "vocab",
      "items": [
        {
          "korean": "구두",
          "indonesian": "Sepatu kulit, sepatu, sepatu (kulit)",
          "image": "/images/textbook/ch15/v1_0_구두.jpg"
        },
        {
          "korean": "모자",
          "indonesian": "Topi, topi",
          "image": "/images/textbook/ch15/v1_1_모자.jpg"
        },
        {
          "korean": "반바지",
          "indonesian": "Celana pendek, celana pendek",
          "image": "/images/textbook/ch15/v1_2_반바지.jpg"
        },
        {
          "korean": "선글라스",
          "indonesian": "kacamata hitam",
          "image": "/images/textbook/ch15/v1_3_선글라스.jpg"
        },
        {
          "korean": "슬리퍼",
          "indonesian": "Sandal, sendal, sandal (utk di dlm rumah)",
          "image": "/images/textbook/ch15/v1_4_슬리퍼.jpg"
        },
        {
          "korean": "신다",
          "indonesian": "Memakai di kaki, memakai (sepatu), asam",
          "image": "/images/textbook/ch15/v1_5_신다.jpg"
        },
        {
          "korean": "쓰다",
          "indonesian": "Memakai di kepala, Pahit, Menulis, Menggunakan, pahit, menggunakan, menulis",
          "image": null
        },
        {
          "korean": "액세서리",
          "indonesian": "Aksesori",
          "image": null
        },
        {
          "korean": "양말",
          "indonesian": "Kaos kaki, kaus kaki",
          "image": "/images/textbook/ch15/v1_8_양말.jpg"
        },
        {
          "korean": "운동화",
          "indonesian": "Sepatu olahraga, sepatu olah raga",
          "image": "/images/textbook/ch15/v1_9_운동화.jpg"
        },
        {
          "korean": "원피스",
          "indonesian": "gaun, terusan",
          "image": "/images/textbook/ch15/v1_10_원피스.jpg"
        },
        {
          "korean": "입다",
          "indonesian": "Memakai di badan, memakai (pakaian), memakai",
          "image": null
        },
        {
          "korean": "잠바",
          "indonesian": "jaket",
          "image": "/images/textbook/ch15/v1_12_잠바.jpg"
        },
        {
          "korean": "장화",
          "indonesian": "Sepatu boot, sapatu boot",
          "image": "/images/textbook/ch15/v1_13_장화.jpg"
        },
        {
          "korean": "청바지",
          "indonesian": "Celana panjang denim, celana jeans",
          "image": "/images/textbook/ch15/v1_14_청바지.jpg"
        },
        {
          "korean": "치마",
          "indonesian": "Rok, rok, chima (rok)",
          "image": "/images/textbook/ch15/v1_15_치마.jpg"
        },
        {
          "korean": "티셔츠",
          "indonesian": "Kaos, kaus",
          "image": "/images/textbook/ch15/v1_16_티셔츠.jpg"
        }
      ],
      "main_image": null
    },
    {
      "title": "Kosakata 2 (어휘 2)",
      "type": "vocab",
      "items": [
        {
          "korean": "갈색",
          "indonesian": "Coklat, coklat muda",
          "image": "/images/textbook/ch15/v2_0_갈색.jpg"
        },
        {
          "korean": "결혼식",
          "indonesian": "Acara pernikahan, Upacara pernikahan, pernikahan",
          "image": "/images/textbook/ch15/v2_1_결혼식.jpg"
        },
        {
          "korean": "까만색",
          "indonesian": "hitam",
          "image": "/images/textbook/ch15/v2_2_까만색.jpg"
        },
        {
          "korean": "노란색",
          "indonesian": "Kuning, kuning",
          "image": "/images/textbook/ch15/v2_3_노란색.jpg"
        },
        {
          "korean": "밝다",
          "indonesian": "Terang, terang",
          "image": "/images/textbook/ch15/v2_4_밝다.jpg"
        },
        {
          "korean": "보라색",
          "indonesian": "ungu",
          "image": "/images/textbook/ch15/v2_5_보라색.jpg"
        },
        {
          "korean": "분홍색",
          "indonesian": "merah muda",
          "image": "/images/textbook/ch15/v2_6_분홍색.jpg"
        },
        {
          "korean": "빨간색",
          "indonesian": "Merah, merah, Warna merah",
          "image": "/images/textbook/ch15/v2_7_빨간색.jpg"
        },
        {
          "korean": "색깔",
          "indonesian": "Warna, warna",
          "image": null
        },
        {
          "korean": "쇼핑몰",
          "indonesian": "Mal perbelanjaan",
          "image": null
        },
        {
          "korean": "어둡다",
          "indonesian": "Gelap, gelap",
          "image": "/images/textbook/ch15/v2_10_어둡다.jpg"
        },
        {
          "korean": "주황색",
          "indonesian": "Jingga, Orange",
          "image": "/images/textbook/ch15/v2_11_주황색.jpg"
        },
        {
          "korean": "초록색",
          "indonesian": "Hijau, hijau",
          "image": "/images/textbook/ch15/v2_12_초록색.jpg"
        },
        {
          "korean": "파란색",
          "indonesian": "Biru, biru, Warna biru",
          "image": "/images/textbook/ch15/v2_13_파란색.jpg"
        },
        {
          "korean": "하나",
          "indonesian": "tuhan, Tuhan",
          "image": null
        },
        {
          "korean": "하얀색",
          "indonesian": "Putih, putih",
          "image": "/images/textbook/ch15/v2_15_하얀색.jpg"
        },
        {
          "korean": "회색",
          "indonesian": "Abu-abu, abu-abu",
          "image": "/images/textbook/ch15/v2_16_회색.jpg"
        }
      ],
      "main_image": null
    }
  ]
}