{
  "chapter": 7,
  "sections": [
    {
      "title": "Kosakata 1 (어휘 1)",
      "type": "vocab",
      "items": [
        {
          "korean": "가을",
          "indonesian": "Musim gugur, musim gugur",
          "image": "/images/textbook/ch7/v1_0_가을.jpg"
        },
        {
          "korean": "겨울",
          "indonesian": "Musim dingin, musim dingin",
          "image": "/images/textbook/ch7/v1_1_겨울.jpg"
        },
        {
          "korean": "계절",
          "indonesian": "Musim, musim",
          "image": null
        },
        {
          "korean": "너무",
          "indonesian": "terlalu",
          "image": null
        },
        {
          "korean": "덥다",
          "indonesian": "Panas (cuaca), panas, panas (cuaca)",
          "image": "/images/textbook/ch7/v1_4_덥다.jpg"
        },
        {
          "korean": "따뜻하다",
          "indonesian": "Hangat, hangat",
          "image": "/images/textbook/ch7/v1_5_따뜻하다.jpg"
        },
        {
          "korean": "뜨겁다",
          "indonesian": "Panas (benda), panas, panas (benda)",
          "image": null
        },
        {
          "korean": "봄",
          "indonesian": "Musim semi, musim semi",
          "image": "/images/textbook/ch7/v1_7_봄.jpg"
        },
        {
          "korean": "쉽다",
          "indonesian": "Mudah, mudah",
          "image": null
        },
        {
          "korean": "시원하다",
          "indonesian": "Sejuk, segar, sejuk",
          "image": "/images/textbook/ch7/v1_9_시원하다.jpg"
        },
        {
          "korean": "어때요?",
          "indonesian": "Bagaimana?, bagaimana",
          "image": null
        },
        {
          "korean": "어렵다",
          "indonesian": "sulit, susah, Sulit",
          "image": null
        },
        {
          "korean": "여름",
          "indonesian": "Musim panas, musim panas",
          "image": "/images/textbook/ch7/v1_12_여름.jpg"
        },
        {
          "korean": "영어",
          "indonesian": "Bahasa Inggris, bahasa inggris",
          "image": null
        },
        {
          "korean": "조금",
          "indonesian": "sedikit",
          "image": null
        },
        {
          "korean": "차갑다",
          "indonesian": "Dingin (benda)",
          "image": null
        },
        {
          "korean": "춥다",
          "indonesian": "Dingin (cuaca), dingin, dingin (cuaca)",
          "image": "/images/textbook/ch7/v1_16_춥다.jpg"
        }
      ],
      "main_image": null
    },
    {
      "title": "Kosakata 2 (어휘 2)",
      "type": "vocab",
      "items": [
        {
          "korean": "비가 그치다",
          "indonesian": "hujan reda",
          "image": "/images/textbook/ch7/v2_0_그치다.jpg"
        },
        {
          "korean": "나쁘다",
          "indonesian": "buruk, jahat",
          "image": "/images/textbook/ch7/v2_1_나쁘다.jpg"
        },
        {
          "korean": "날씨",
          "indonesian": "cuaca",
          "image": "/images/textbook/ch7/v2_2_날씨.jpg"
        },
        {
          "korean": "눈이\t오다",
          "indonesian": "turun salju",
          "image": "/images/textbook/ch7/v2_3_눈이_오다.jpg"
        },
        {
          "korean": "많이",
          "indonesian": "Banyak, sangat, banyak",
          "image": null
        },
        {
          "korean": "맑다",
          "indonesian": "Jernih, cerah, jernih",
          "image": null
        },
        {
          "korean": "바람이\t불다",
          "indonesian": "bertiup angin",
          "image": "/images/textbook/ch7/v2_6_바람이_불다.jpg"
        },
        {
          "korean": "별로",
          "indonesian": "tidak terlalu",
          "image": null
        },
        {
          "korean": "여보세요?",
          "indonesian": "halo",
          "image": null
        },
        {
          "korean": "정말",
          "indonesian": "sangat, sungguh",
          "image": null
        },
        {
          "korean": "좋다",
          "indonesian": "bagus, baik",
          "image": null
        },
        {
          "korean": "흐리다",
          "indonesian": "Mengalir, mendung",
          "image": "/images/textbook/ch7/v2_12_흐리다.jpg"
        }
      ],
      "main_image": null
    }
  ]
}